MANIFEST.in
README.rst
setup.py
docs/HISTORY.txt
docs/INSTALL.txt
docs/LICENSE.GPL
docs/LICENSE.txt
src/monet/__init__.py
src/monet.calendar.star.egg-info/PKG-INFO
src/monet.calendar.star.egg-info/SOURCES.txt
src/monet.calendar.star.egg-info/dependency_links.txt
src/monet.calendar.star.egg-info/entry_points.txt
src/monet.calendar.star.egg-info/namespace_packages.txt
src/monet.calendar.star.egg-info/not-zip-safe
src/monet.calendar.star.egg-info/requires.txt
src/monet.calendar.star.egg-info/top_level.txt
src/monet/calendar/__init__.py
src/monet/calendar/star/__init__.py
src/monet/calendar/star/configure.zcml
src/monet/calendar/star/tests.py
src/monet/calendar/star/profiles/default/metadata.xml